odoo/addons/product_customerinfo_invoice/README.rst
odoo/addons/product_customerinfo_invoice/__init__.py
odoo/addons/product_customerinfo_invoice/__manifest__.py
odoo/addons/product_customerinfo_invoice/i18n/product_customerinfo_invoice.pot
odoo/addons/product_customerinfo_invoice/models/__init__.py
odoo/addons/product_customerinfo_invoice/models/account_move_line.py
odoo/addons/product_customerinfo_invoice/readme/CONTRIBUTORS.md
odoo/addons/product_customerinfo_invoice/readme/DESCRIPTION.md
odoo/addons/product_customerinfo_invoice/static/description/icon.png
odoo/addons/product_customerinfo_invoice/static/description/index.html
odoo/addons/product_customerinfo_invoice/tests/__init__.py
odoo/addons/product_customerinfo_invoice/tests/test_product_customerinfo_invoice.py
odoo/addons/product_customerinfo_invoice/views/account_move_view.xml
odoo_addon_product_customerinfo_invoice-18.0.1.0.0.2.dist-info/METADATA
odoo_addon_product_customerinfo_invoice-18.0.1.0.0.2.dist-info/WHEEL
odoo_addon_product_customerinfo_invoice-18.0.1.0.0.2.dist-info/top_level.txt
odoo_addon_product_customerinfo_invoice-18.0.1.0.0.2.dist-info/RECORD
